Mopidy_Radio_Rough_HTML-31.41.5926.dist-info/DESCRIPTION.rst
Mopidy_Radio_Rough_HTML-31.41.5926.dist-info/METADATA
Mopidy_Radio_Rough_HTML-31.41.5926.dist-info/RECORD
Mopidy_Radio_Rough_HTML-31.41.5926.dist-info/WHEEL
Mopidy_Radio_Rough_HTML-31.41.5926.dist-info/entry_points.txt
Mopidy_Radio_Rough_HTML-31.41.5926.dist-info/metadata.json
Mopidy_Radio_Rough_HTML-31.41.5926.dist-info/top_level.txt
mopidy_radio_rough_html/__init__.py
mopidy_radio_rough_html/ext.conf
mopidy_radio_rough_html/htmltemplates.py
mopidy_radio_rough_html/radio_rough.desktop
mopidy_radio_rough_html/icons/details_off.png
mopidy_radio_rough_html/icons/details_on.png
mopidy_radio_rough_html/icons/favorited.png
mopidy_radio_rough_html/icons/favorites_add.png
mopidy_radio_rough_html/icons/ffwd-2.png
mopidy_radio_rough_html/icons/ffwd-3.png
mopidy_radio_rough_html/icons/ffwd-4.png
mopidy_radio_rough_html/icons/file_folder.png
mopidy_radio_rough_html/icons/history.png
mopidy_radio_rough_html/icons/home.png
mopidy_radio_rough_html/icons/loop_this.png
mopidy_radio_rough_html/icons/next.png
mopidy_radio_rough_html/icons/play.png
mopidy_radio_rough_html/icons/play_next.png
mopidy_radio_rough_html/icons/play_pause.png
mopidy_radio_rough_html/icons/playing.png
mopidy_radio_rough_html/icons/previous.png
mopidy_radio_rough_html/icons/queue_add.png
mopidy_radio_rough_html/icons/queue_remove.png
mopidy_radio_rough_html/icons/queue_show.png
mopidy_radio_rough_html/icons/reboot.png
mopidy_radio_rough_html/icons/refresh_is_off.png
mopidy_radio_rough_html/icons/refresh_is_on.png
mopidy_radio_rough_html/icons/rewind-2.png
mopidy_radio_rough_html/icons/rewind-3.png
mopidy_radio_rough_html/icons/rewind-4.png
mopidy_radio_rough_html/icons/settings.png
mopidy_radio_rough_html/icons/ucc.gif
mopidy_radio_rough_html/icons/ucc.png
mopidy_radio_rough_html/icons/ucc_64.png
mopidy_radio_rough_html/icons/volume-1.png
mopidy_radio_rough_html/icons/volume-1_sel.png
mopidy_radio_rough_html/icons/volume-2.png
mopidy_radio_rough_html/icons/volume-2_sel.png
mopidy_radio_rough_html/icons/volume-3.png
mopidy_radio_rough_html/icons/volume-3_sel.png
mopidy_radio_rough_html/icons/volume-4.png
mopidy_radio_rough_html/icons/volume-4_sel.png
mopidy_radio_rough_html/icons/volume_mute.png
mopidy_radio_rough_html/icons/volume_mute_sel.png
